Metadata-Version: 2.1
Name: hyperdock
Version: 0.19.2
Summary: A distributed hyperparameter optimizer for machine learning that lives in Docker
Home-page: http://github.com/ErikGartner/hyperdock
Author: Erik Gärtner
Author-email: erik@gartner.io
License: Apache 2.0
Keywords: hyperparameter,optimization,docker
Platform: UNKNOWN
Classifier: Development Status :: 4 - Beta
Classifier: Intended Audience :: Developers
Classifier: License :: OSI Approved
Classifier: Natural Language :: English
Classifier: Operating System :: Unix
Classifier: Programming Language :: Python :: 3.6
Classifier: Operating System :: OS Independent
Provides-Extra: tests
